py_persian_tts/__init__.py
py_persian_tts/tts.py
py_persian_tts/utils.py
py_persian_tts/voices.py
py_persian_tts-1.2.2.dist-info/METADATA
py_persian_tts-1.2.2.dist-info/WHEEL
py_persian_tts-1.2.2.dist-info/entry_points.txt
py_persian_tts-1.2.2.dist-info/top_level.txt
py_persian_tts-1.2.2.dist-info/RECORD
