Metadata-Version: 2.4
Name: py_persian_tts
Version: 1.2.2
Summary: کتابخانه تبدیل متن به گفتار فارسی با پشتیبانی از چندین شخصیت صوتی
Home-page: https://github.com/amirhossinpython/py_persian_tts
Author: AmirhosseinPython
Author-email: amirhossinpython03@gmail.com
Keywords: persian tts text-to-speech farsi
Classifier: Development Status :: 3 - Alpha
Classifier: Intended Audience :: Developers
Classifier: Programming Language :: Python :: 3
Classifier: License :: OSI Approved :: MIT License
Classifier: Operating System :: OS Independent
Classifier: Natural Language :: Persian
Classifier: Topic :: Multimedia :: Sound/Audio :: Speech
Requires-Python: >=3.8
Requires-Dist: requests>=2.31.0
Requires-Dist: aiohttp>=3.9.0
Requires-Dist: gtts>=2.3.0
Dynamic: author
Dynamic: author-email
Dynamic: classifier
Dynamic: description
Dynamic: description-content-type
Dynamic: home-page
Dynamic: keywords
Dynamic: requires-dist
Dynamic: requires-python
Dynamic: summary
